kerykeion_mcp/__init__.py
kerykeion_mcp/china_cities.json
kerykeion_mcp/core.py
kerykeion_mcp/server.py
kerykeion_mcp-1.0.0.dist-info/METADATA
kerykeion_mcp-1.0.0.dist-info/WHEEL
kerykeion_mcp-1.0.0.dist-info/entry_points.txt
kerykeion_mcp-1.0.0.dist-info/licenses/LICENSE
kerykeion_mcp-1.0.0.dist-info/RECORD
