Metadata-Version: 2.4
Name: kerykeion-mcp
Version: 1.0.0
Summary: 基于 Kerykeion 库的占星计算 MCP 服务器
Project-URL: Homepage, https://github.com/yourusername/kerykeion-mcp
Project-URL: Documentation, https://github.com/yourusername/kerykeion-mcp#readme
Project-URL: Repository, https://github.com/yourusername/kerykeion-mcp.git
Project-URL: Issues, https://github.com/yourusername/kerykeion-mcp/issues
Author-email: Your Name <your.email@example.com>
License: MIT
License-File: LICENSE
Classifier: Development Status :: 4 - Beta
Classifier: Intended Audience :: Developers
Classifier: License :: OSI Approved :: MIT License
Classifier: Programming Language :: Python :: 3
Classifier: Programming Language :: Python :: 3.8
Classifier: Programming Language :: Python :: 3.9
Classifier: Programming Language :: Python :: 3.10
Classifier: Programming Language :: Python :: 3.11
Classifier: Programming Language :: Python :: 3.12
Classifier: Topic :: Scientific/Engineering :: Astronomy
Classifier: Topic :: Software Development :: Libraries :: Python Modules
Requires-Python: >=3.8
Requires-Dist: kerykeion>=4.0.0
Requires-Dist: pydantic>=2.0.0
Provides-Extra: dev
Requires-Dist: black>=23.0.0; extra == 'dev'
Requires-Dist: flake8>=6.0.0; extra == 'dev'
Requires-Dist: isort>=5.0.0; extra == 'dev'
Requires-Dist: mypy>=1.0.0; extra == 'dev'
Requires-Dist: pytest-cov>=4.0.0; extra == 'dev'
Requires-Dist: pytest>=7.0.0; extra == 'dev'
